oactool/__init__.py
oactool/main.py
oactool/parsers/__init__.py
oactool/parsers/fish.py
oactool/parsers/man.py
oactool/renderers/__init__.py
oactool/renderers/docopt.py
oactool/renderers/fish.py
oactool/schema.py
oactool/spec_parse.py
oactool-0.1.5.dist-info/entry_points.txt
oactool-0.1.5.dist-info/LICENSE
oactool-0.1.5.dist-info/WHEEL
oactool-0.1.5.dist-info/METADATA
oactool-0.1.5.dist-info/RECORD
